<?xml version="1.0" encoding="UTF-8"?>
<Module>
<ModulePrefs title="絵文字化でしりとり(日本語版) viewer">
<Require feature="opensocial-0.7"/>
</ModulePrefs>
<Content type="html">
<![CDATA[
<script type="text/javascript" src="http://hackathon-jp.googlecode.com/svn/trunk/OpenSocial20090221/Wall/capping/jquery-1.2.6.js"></script>
<script type="text/javascript">
/**
 *
 *
 */
function init() {
    loadFriends();

    $("#btn_submit").bind("click", function(){
        if(validateData()) {
            sendTextToAFriend();
        }
    });
}

/**
 *
 *
 */
function loadFriends() {
    var req = opensocial.newDataRequest();
    req.add(req.newFetchPersonRequest("VIEWER"), "viewer");
    req.add(req.newFetchPeopleRequest("VIEWER_FRIENDS"), "viewer_friends");
    req.add(req.newFetchPersonAppDataRequest("VIEWER", "cap"), "viewer_cap");
    req.add(req.newFetchPersonAppDataRequest("VIEWER_FRIENDS", "cap"), "viewer_friends_cap");
    req.send(handleLoadFriends);
}

/**
 *
 *
 */
function handleLoadFriends(data) {
    if(data.hadError()) {
        alert('error');
        alert(data.getErrorMessage());
        return;
    }
    onLoadFriends(data);
}

/**
 *
 *
 */
function onLoadFriends(data) {
    var viewer = data.get("viewer").getData();
    var viewerFriends = data.get("viewer_friends").getData();
    var viewer_cap = data.get("viewer_cap").getData();
    var viewer_friends_cap = data.get("viewer_friends_cap").getData();

    var html = new Array();
    html.push("<select id='person'>");
    viewerFriends.each(function(person){
        html.push("<option value='" + person.getId() + "'>" + person.getDisplayName() + "</option>");
    });
    html.push("</select>");
    html.push("と絵文字しりとりする．");
    $("#select").html(html.join(""));

    updateGiveList(data);
    updateReceivedList(data);
}

/**
 *
 *
 */
function updateGiveList(data) {
    var viewer = data.get("viewer").getData();
    var viewerFriends = data.get("viewer_friends").getData();
    var viewer_cap = data.get("viewer_cap").getData();
    var viewer_friends_cap = data.get("viewer_friends_cap").getData();


}

/**
 *
 *
 */
function updateReceivedList(data) {
    var viewer = data.get("viewer").getData();
    var viewerFriends = data.get("viewer_friends").getData();
    var viewer_cap = data.get("viewer_cap").getData();
    var viewer_friends_cap = data.get("viewer_friends_cap").getData();

    viewerFriends.each(function(person){
        var personData = viewer_friends_cap[person.getId()];
    });
    alert(viewer.getId());
    var hoge = viewer.getId();
    var json = viewer_friends_cap[viewer.getId()]["cap"];

    //alert(json);
    
    givenCap = gadets.util.parse(gadets.util.unescapeString(json));
    alert(givenCap);
}

/**
 *
 *
 */
function sendTextToAFriend() {
    var cappingText = $("#capping").val();
    var personId = $("#person").val();
    alert(personId);

    var sendText = {};
    var cap_data = {};
    cap_data["cap"] = cappingText;
    cap_data["number"] = 1;
    cap_data["flg"] = 1;
    sendText[personId] = cap_data;
    //sendText[personId] = cappingText;
    //sendText[personId]["flg"] = 1;
    var json = gadgets.json.stringify(sendText);
    alert(json);

    var req = opensocial.newDataRequest();
    req.add(req.newUpdatePersonAppDataRequest("VIEWER", "cap", json));
    req.add(req.newFetchPersonRequest("VIEWER"), "viewer");
    req.add(req.newFetchPeopleRequest("VIEWER_FRIENDS"), "viewer_friends");
    req.add(req.newFetchPersonAppDataRequest("VIEWER", "cap"), "viewer_cap");
    req.add(req.newFetchPersonAppDataRequest("VIEWER_FRIENDS", "cap"), "viewer_friends_cap");
    req.send(handleLoadFriends);
}

/**
 *
 *
 */
function validateData(){
    return true;
}

gadgets.util.registerOnLoadHandler(init);
</script>
<div id="select"></div>
<div id="capping"><div id="capping_area">ここに経歴が入ります．</div></div>
<div id="text"><input type="text" id ="capping" name="capping" value="" /><input type="submit" id="btn_submit" name="btn_submit" value="送る"></div>
<div id="friends"></div>
]]>
</Content>
<Content type="html">
<![CDATA[
]]>
</Content>
</Module>
