<?xml version="1.0" encoding="UTF-8" ?>
<Module>
	<ModulePrefs title="トゥルースオブ県" description="県民ガジェット">
		<Require feature="opensocial-0.8"/>
		<Require feature="dynamic-height" />
	</ModulePrefs>
	<Content type="html" view="canvas"><![CDATA[
	
    	<script type="text/javascript" src="http://ec2-174-129-131-70.compute-1.amazonaws.com/jquery-1.2.6.js"></script>
		<script type="text/javascript" src="http://ec2-174-129-131-70.compute-1.amazonaws.com/jquery.inc-5.js"></script>
		<script type="text/javascript" src="http://ec2-174-129-131-70.compute-1.amazonaws.com/jsdeferred.js"></script>
		<script type="text/javascript" src="http://opensocial-jquery.googlecode.com/svn/trunk/features/opensocial-jquery/opensocial-jquery.min.js"></script>
		<script type="text/javascript" src="http://ec2-174-129-131-70.compute-1.amazonaws.com/question.js"></script>
		<script type="text/javascript">
			gadgets.util.registerOnLoadHandler(init);
		</script>
	
	]]></Content>
</Module>